claudeguard/__init__.py
claudeguard/builtin_profiles.py
claudeguard/cli.py
claudeguard/default_rules.py
claudeguard/hook.py
claudeguard/models.py
claudeguard/pattern_matcher.py
claudeguard/permission_decision.py
claudeguard/profile_loader.py
claudeguard-0.1.3.dist-info/METADATA
claudeguard-0.1.3.dist-info/WHEEL
claudeguard-0.1.3.dist-info/entry_points.txt
claudeguard-0.1.3.dist-info/licenses/LICENSE
claudeguard-0.1.3.dist-info/RECORD
