Metadata-Version: 2.4
Name: claudeguard
Version: 0.1.3
Summary: Claude Code security guard - an alternative Claude Code permission framework
Project-URL: Homepage, https://github.com/tarovard/claudeguard
Project-URL: Repository, https://github.com/tarovard/claudeguard.git
Project-URL: Issues, https://github.com/tarovard/claudeguard/issues
Author-email: claudeguard contributors <tarovard@users.noreply.github.com>
License-Expression: MIT
License-File: LICENSE
Keywords: ai-tools,claude-code,cli,hook,pattern-matching,permissions,security
Classifier: Development Status :: 5 - Production/Stable
Classifier: Intended Audience :: Developers
Classifier: License :: OSI Approved :: MIT License
Classifier: Operating System :: OS Independent
Classifier: Programming Language :: Python :: 3
Classifier: Programming Language :: Python :: 3.10
Classifier: Programming Language :: Python :: 3.11
Classifier: Programming Language :: Python :: 3.12
Classifier: Topic :: Security
Classifier: Topic :: Software Development
Classifier: Topic :: System :: Shells
Classifier: Typing :: Typed
Requires-Python: >=3.10
Requires-Dist: click>=8.0.0
Requires-Dist: pyyaml>=6.0
Provides-Extra: dev
Requires-Dist: mypy>=1.0; extra == 'dev'
Requires-Dist: pre-commit>=3.0; extra == 'dev'
Requires-Dist: pytest>=7.0; extra == 'dev'
Requires-Dist: ruff>=0.1.0; extra == 'dev'
Provides-Extra: docs
